pylbcapi/__init__.py
pylbcapi-0.1.dist-info/METADATA
pylbcapi-0.1.dist-info/RECORD
pylbcapi-0.1.dist-info/WHEEL
pylbcapi-0.1.dist-info/top_level.txt
